archimedes/__init__.py
archimedes/auth.py
archimedes/configuration.py
archimedes/data/__init__.py
archimedes/data/api/__init__.py
archimedes/data/api/forecast.py
archimedes/data/api/intraday.py
archimedes/data/api/metadata.py
archimedes/data/api/observation.py
archimedes/data/api/prediction.py
archimedes/data/api/rk_within_day.py
archimedes/data/api/umm.py
archimedes/data/common.py
archimedes/data/types.py
archimedes/logger.py
archimedes/token_cache.py
archimedes/utils/__init__.py
archimedes/utils/api_request.py
archimedes/utils/date.py
archimedes/utils/environ_context.py
archimedes/utils/format.py
archimedes/utils/idempotency.py
archimedes/utils/split/__init__.py
archimedes/utils/split/config.py
archimedes/utils/split/split.py
archimedes/utils/threaded_executor.py
archimedes/version.py
archimedes_python_client-4.20.3.dist-info/METADATA
archimedes_python_client-4.20.3.dist-info/WHEEL
archimedes_python_client-4.20.3.dist-info/RECORD
