Metadata-Version: 2.1
Name: archimedes-python-client
Version: 4.20.3
Summary: The Python library for Archimedes
License: Apache-2.0
Author: Optimeering AS
Author-email: dev@optimeering.com
Requires-Python: >=3.9,<3.12
Classifier: License :: OSI Approved :: Apache Software License
Classifier: Programming Language :: Python :: 3
Classifier: Programming Language :: Python :: 3.9
Classifier: Programming Language :: Python :: 3.10
Classifier: Programming Language :: Python :: 3.11
Requires-Dist: cachetools (>=5.2.0,<6.0.0)
Requires-Dist: msal (>=1.10.0,<2.0.0)
Requires-Dist: msal-extensions (>=1.0.0,<2.0.0)
Requires-Dist: orjson (>=3.8.7,<4.0.0)
Requires-Dist: pandas (>=1.0.5)
Requires-Dist: requests (>=2.27.0)
Requires-Dist: retrying (>=1.3.4,<2.0.0)
